{
  "data": {
    "site_name": "TheWire",
    "home_page_url": "https://p.thewire.in",
    "ref_category_html": "<a href='https://p.thewire.in' style='height: 36px' class='desktop-only'> <span style='font-size: 28px;margin-top: 0px;font-family: cabin;color: #22C5F9;display: inline-block;'> <span style='background: black;display: inline-block;float: left;margin-right: 2px;width: 26px;height: 36px;font-weight: bold;text-align: center;line-height: 36px; margin-top: -3px;'>#</span> <span style='background: black;display: inline-block;float: left;margin-right: 2px;width: 26px;height: 36px;font-weight: bold;text-align: center;line-height: 36px; margin-top: -3px;'>S</span> <span style='background: black;display: inline-block;float: left;margin-right: 2px;width: 26px;height: 36px;font-weight: bold;text-align: center;line-height: 36px; margin-top: -3px;'>T</span> <span style='background: black;display: inline-block;float: left;margin-right: 2px;width: 26px;height: 36px;font-weight: bold;text-align: center;line-height: 36px; margin-top: -3px;'>I</span> <span style='background: black;display: inline-block;float: left;margin-right: 2px;width: 26px;height: 36px;font-weight: bold;text-align: center;line-height: 36px; margin-top: -3px;'>N</span> <span style='background: black;display: inline-block;float: left;margin-right: 2px;width: 26px;height: 36px;font-weight: bold;text-align: center;line-height: 36px; margin-top: -3px;'>K</span> </span> </a> <a href='https://p.thewire.in' style='height: 31px' class='mobile-only'> <span style='font-size: 20px;margin-top: 0px;font-family: cabin;color: #22C5F9;display: inline-block;'> <span style='background: black;display: inline-block;float: left;margin-right: 2px;width: 21px;height: 31px;font-weight: bold;text-align: center;line-height: 31px; margin-top: -1px;'>#</span> <span style='background: black;display: inline-block;float: left;margin-right: 2px;width: 21px;height: 31px;font-weight: bold;text-align: center;line-height: 31px; margin-top: -1px;'>S</span> <span style='background: black;display: inline-block;float: left;margin-right: 2px;width: 21px;height: 31px;font-weight: bold;text-align: center;line-height: 31px; margin-top: -1px;'>T</span> <span style='background: black;display: inline-block;float: left;margin-right: 2px;width: 21px;height: 31px;font-weight: bold;text-align: center;line-height: 31px; margin-top: -1px;'>I</span> <span style='background: black;display: inline-block;float: left;margin-right: 2px;width: 21px;height: 31px;font-weight: bold;text-align: center;line-height: 31px; margin-top: -1px;'>N</span> <span style='background: black;display: inline-block;float: left;margin-right: 2px;width: 21px;height: 31px;font-weight: bold;text-align: center;line-height: 31px; margin-top: -1px;'>K</span> </span> </a>",
    "show_by_publisher_in_header": true,
    "summary": "#Stink, by the Wire - News and coverage of sanitation, manual scavenging and the intersections of caste, policy and gender.",
    "streams": [
      {
        "url": "https://p.thewire.in/445ea87bd708c3d1cb90e0d0/index.json"
      },
      {
        "url": "https://p.thewire.in/9db58017fc0acade3e95b740/index.json"
      },
      {
        "url": "https://p.thewire.in/7e3a9addd233561284c18656/index.json"
      },
      {
        "url": "https://p.thewire.in/11951c04828b286e29207f38/index.json"
      },
      {
        "url": "https://p.thewire.in/93e3f7a066ea0721bf455605/index.json"
      }
    ]
  }
}
